{
	"files": [
		{
			"path": "script.js",
			"bookmarks": [
				{
					"line": 0,
					"column": 0,
					"label": ""
				},
				{
					"line": 27,
					"column": 0,
					"label": ""
				},
				{
					"line": 166,
					"column": 0,
					"label": ""
				}
			]
		},
		{
			"path": "script-connect-four.js",
			"bookmarks": [
				{
					"line": 0,
					"column": 0,
					"label": ""
				},
				{
					"line": 33,
					"column": 0,
					"label": ""
				},
				{
					"line": 101,
					"column": 0,
					"label": ""
				},
				{
					"line": 151,
					"column": 0,
					"label": ""
				}
			]
		},
		{
			"path": "script-console.js",
			"bookmarks": [
				{
					"line": 25,
					"column": 0,
					"label": ""
				},
				{
					"line": 123,
					"column": 0,
					"label": ""
				},
				{
					"line": 162,
					"column": 0,
					"label": ""
				}
			]
		},
		{
			"path": "style.css",
			"bookmarks": [
				{
					"line": 18,
					"column": 0,
					"label": ""
				},
				{
					"line": 26,
					"column": 0,
					"label": ""
				},
				{
					"line": 42,
					"column": 0,
					"label": ""
				},
				{
					"line": 49,
					"column": 0,
					"label": ""
				}
			]
		}
	]
}